[
  {
    "video_id": "DCIL2nvU4x8",
    "title": "A shark-deterrent wetsuit (and it's not what you think) | Hamish Jolly",
    "video_tags": [
      "Int",
      "US"
    ],
    "duration": "12:33"
  },
  {
    "video_id": "MynNG2IRZDI",
    "title": "POKEMON GO New Official Trailer (2018)",
    "video_tags": [
      "Basic",
      "US"
    ],
    "duration": "01:10"
  },
  {
    "video_id": "4YugijSOHQA",
    "title": "Jacque Fresco - Building Cities - FbD Outtakes",
    "video_tags": [
      "Int",
      "US"
    ],
    "duration": "06:37"
  },
  {
    "video_id": "oyM3PG4pn-M",
    "title": "10 Pranks For Back To School 2017 Using School Supplies!",
    "video_tags": [
      "Int",
      "US"
    ],
    "duration": "15:45"
  },
  {
    "video_id": "xM9S4QiEHEY",
    "title": "Proving The Earth Is Flat!",
    "video_tags": [
      "Int",
      "US"
    ],
    "duration": "10:24"
  },
  {
    "video_id": "YDvbDiJZpy0",
    "title": "Meet the inventor of the electronic spreadsheet | Dan Bricklin",
    "video_tags": [
      "Int",
      "US"
    ],
    "duration": "12:01"
  },
  {
    "video_id": "LgUCyWhJf6s",
    "title": "What is Emotional Intelligence?",
    "video_tags": [
      "Int",
      "US"
    ],
    "duration": "05:29"
  },
  {
    "video_id": "GZ-N5o1BwJ0",
    "title": "What is asthma? | #aumsum #kids #science #education #children",
    "video_tags": [
      "Basic",
      "US"
    ],
    "duration": "01:29"
  },
  {
    "video_id": "CNOgsWn0S_8",
    "title": "The Forrest Gump Suite || Piano Cover",
    "video_tags": [
      "Basic",
      "US"
    ],
    "duration": "06:56"
  },
  {
    "video_id": "roXTB6pQn28",
    "title": "\"Interpassion\" / \"Ba$$in\" | Yelle",
    "video_tags": [
      "Basic",
      "US"
    ],
    "duration": "07:23"
  },
  {
    "video_id": "ta2Wvy9F_gA",
    "title": "A climate solution where all sides can win | Ted Halstead",
    "video_tags": [
      "Int",
      "US"
    ],
    "duration": "13:08"
  },
  {
    "video_id": "lrewt5USFk0",
    "title": "100 English Homophones with American Accent",
    "video_tags": [
      "Basic",
      "US"
    ],
    "duration": "09:22"
  },
  {
    "video_id": "fvTsFjDuag8",
    "title": "Valgrind",
    "video_tags": [
      "Int"
    ],
    "duration": "12:26"
  },
  {
    "video_id": "0YFh38ImZ58",
    "title": "CIVILIZATION VI - First Look: Egypt",
    "video_tags": [
      "Basic",
      "US"
    ],
    "duration": "01:53"
  },
  {
    "video_id": "y5nbWUOc9tY",
    "title": "Julian Treasure: Why architects need to use their ears",
    "video_tags": [
      "Int",
      "US"
    ],
    "duration": "09:52"
  },
  {
    "video_id": "MOrwW6avyGU",
    "title": "Sand Planet (English Cover)【JubyPhonic】砂の惑星",
    "video_tags": [
      "Basic",
      "US"
    ],
    "duration": "04:23"
  }
]