[
  {
    "video_id": "cDiHQ3B31WQ",
    "title": "Sabrina Claudio - Naked (Official Audio)",
    "video_tags": [
      "Basic",
      "US"
    ],
    "duration": "03:10"
  },
  {
    "video_id": "G01SFcou6P4",
    "title": "Master AT, ON, IN with the TRIANGLE method",
    "video_tags": [
      "Basic",
      "US"
    ],
    "duration": "07:01"
  },
  {
    "video_id": "Czg_9C7gw0o",
    "title": "Is Social Media Hurting Your Mental Health? | Bailey Parnell | TEDxRyersonU",
    "video_tags": [
      "Int",
      "US"
    ],
    "duration": "14:45"
  },
  {
    "video_id": "F46r-_jPPHY",
    "title": "System Of A Down - War? (Official Video)",
    "video_tags": [
      "Basic",
      "US"
    ],
    "duration": "03:12"
  },
  {
    "video_id": "V1JrI2Y3DnM",
    "title": "【How to Play KanColle】In Game Tutorial",
    "video_tags": [
      "Int",
      "US"
    ],
    "duration": "07:22"
  },
  {
    "video_id": "gqVgxJCDAkU",
    "title": "Welcome to The City of London",
    "video_tags": [
      "Basic",
      "UK"
    ],
    "duration": "03:18"
  },
  {
    "video_id": "57_fEU3pw2M",
    "title": "Common Diarrhoea Misconceptions; Getting the Facts Straight | A Quick Guide with Dr Christian Jessen",
    "video_tags": [
      "Int",
      "UK"
    ],
    "duration": "02:49"
  },
  {
    "video_id": "OJITRDBEbp4",
    "title": "Goldfinger - Here In Your Bedroom",
    "video_tags": [
      "Basic",
      "US"
    ],
    "duration": "03:18"
  },
  {
    "video_id": "jcD0Daqc3Yw",
    "title": "The Big Sick Trailer #1 (2017) | Movieclips Trailers",
    "video_tags": [
      "Basic",
      "US"
    ],
    "duration": "02:28"
  },
  {
    "video_id": "zEoolkhAlIU",
    "title": "What Caused 2 Pit Bulls to Kill Their Owner?",
    "video_tags": [
      "Basic",
      "US"
    ],
    "duration": "01:34"
  },
  {
    "video_id": "6MnCKHh2UEM",
    "title": "BEST Advice For Online English Classes With Private Teachers",
    "video_tags": [
      "Int",
      "US"
    ],
    "duration": "12:54"
  },
  {
    "video_id": "kKAkj3rCBEo",
    "title": "Substitute Teacher Problems",
    "video_tags": [
      "Basic",
      "US"
    ],
    "duration": "03:10"
  },
  {
    "video_id": "V9Znhvbyo_c",
    "title": "Let's Play Minecraft - Episode 10 - Wipeout Part 1 | Rooster Teeth",
    "video_tags": [
      "Advanced",
      "US"
    ],
    "duration": "31:59"
  },
  {
    "video_id": "dfMELZBBVRY",
    "title": "[MV] AOA _ Bing Bing(빙빙)",
    "video_tags": [
      "Basic",
      "US"
    ],
    "duration": "03:45"
  },
  {
    "video_id": "vPGPeDyiF_I",
    "title": "Learn 17 Business Abbreviations & Acronyms in English",
    "video_tags": [
      "Int",
      "US"
    ],
    "duration": "10:01"
  },
  {
    "video_id": "e2IpYd6Pu3s",
    "title": "Izzy Bizu - White Tiger (Official Video)",
    "video_tags": [
      "Basic",
      "US"
    ],
    "duration": "02:56"
  }
]