[
  {
    "video_id": "ztiHRiFXtoc",
    "title": "Exercise vs Diet",
    "video_tags": [
      "Int",
      "US"
    ],
    "duration": "02:28"
  },
  {
    "video_id": "aHC3i6N9Wvk",
    "title": "How Similar Are Chinese and Japanese?",
    "video_tags": [
      "Int",
      "US"
    ],
    "duration": "12:52"
  },
  {
    "video_id": "oZI2prSD1EI",
    "title": "Britney Spears Reads a Bedtime Story",
    "video_tags": [
      "Basic",
      "US"
    ],
    "duration": "00:47"
  },
  {
    "video_id": "NiMgOklgeos",
    "title": "The beauty of human skin in every color | Angélica Dass",
    "video_tags": [
      "Int",
      "Other"
    ],
    "duration": "11:28"
  },
  {
    "video_id": "_U7FhrTXziQ",
    "title": "Nina Nesbitt - The Sun Will Come Up, The Seasons Will Change (Official Audio)",
    "video_tags": [
      "Basic",
      "US"
    ],
    "duration": "03:33"
  },
  {
    "video_id": "cy9GregPIA4",
    "title": "Claire Danes Loves Techno",
    "video_tags": [
      "Int",
      "US"
    ],
    "duration": "03:33"
  },
  {
    "video_id": "GGc96DX_iTg",
    "title": "Špiónky ve filmu (CZ titulky) 4/9",
    "video_tags": [
      "Int",
      "US"
    ],
    "duration": "09:55"
  },
  {
    "video_id": "MwhJ77_Sy4g",
    "title": "XXXTENTACION - I Don't Wanna Do This Anymore",
    "video_tags": [
      "Basic",
      "US"
    ],
    "duration": "01:29"
  },
  {
    "video_id": "WGtbWH-e70Q",
    "title": "7 pitching velocity killers - Fix these and throw GAS!",
    "video_tags": [
      "Int",
      "US"
    ],
    "duration": "07:48"
  },
  {
    "video_id": "dQmaMOxwaQI",
    "title": "How to transform sinking cities into landscapes that fight floods | Kotchakorn Voraakhom",
    "video_tags": [
      "Int",
      "US"
    ],
    "duration": "12:31"
  },
  {
    "video_id": "d1W7wqXD_b0",
    "title": "LITERATURE - Virginia Woolf",
    "video_tags": [
      "Advanced",
      "UK"
    ],
    "duration": "10:16"
  },
  {
    "video_id": "0VIaL7lbgv4",
    "title": "Crime and Outrage",
    "video_tags": [
      "Int",
      "US"
    ],
    "duration": "03:49"
  },
  {
    "video_id": "mv4MRmwXJMM",
    "title": "Kygo - Kids in Love ft. The Night Game (Official Audio)",
    "video_tags": [
      "Basic",
      "US"
    ],
    "duration": "04:25"
  },
  {
    "video_id": "l4eUJw79fZ8",
    "title": "Charts That Count: how to get more women in the workforce",
    "video_tags": [
      "Basic",
      "US"
    ],
    "duration": "04:10"
  },
  {
    "video_id": "TKM0P3XlMNA",
    "title": "Introduction to the Solar System: Crash Course Astronomy #9",
    "video_tags": [
      "Advanced",
      "US"
    ],
    "duration": "10:17"
  },
  {
    "video_id": "rlR4PJn8b8I",
    "title": "Game of Thrones | Season 8 | Official Trailer (HBO)",
    "video_tags": [
      "Basic",
      "US"
    ],
    "duration": "02:03"
  }
]