[
  {
    "video_id": "jn0M9qQJEuw",
    "title": "The Jaw-Dropping Ultimate Backyard Escape | The Pool Master",
    "video_tags": [
      "Int",
      "UK"
    ],
    "duration": "04:20"
  },
  {
    "video_id": "1r2nLKdcVRI",
    "title": "Lima City Video Guide | Expedia",
    "video_tags": [
      "Int",
      "Other"
    ],
    "duration": "06:51"
  },
  {
    "video_id": "HGS70F1v8tA",
    "title": "Jennifer Lopez Gets Emotional Discussing Alex Rodriguez and Directing Her Daughter",
    "video_tags": [
      "Basic",
      "US"
    ],
    "duration": "04:05"
  },
  {
    "video_id": "pmCJIk5H5ZI",
    "title": "Isle of Dogs - I Won't Hurt You (Lyric)",
    "video_tags": [
      "Basic",
      "US"
    ],
    "duration": "02:29"
  },
  {
    "video_id": "R3t1cg2ZOxc",
    "title": "No Roads, No Cars, Just Boats",
    "video_tags": [
      "Basic",
      "US"
    ],
    "duration": "02:39"
  },
  {
    "video_id": "OJuuEGCgjW8",
    "title": "6.4 Magnitude Earthquake Topples Buildings In Taiwan",
    "video_tags": [
      "Basic",
      "US"
    ],
    "duration": "00:30"
  },
  {
    "video_id": "ay4BUXDONL8",
    "title": "At 88rising, East Meets West, One Viral Hit at a Time",
    "video_tags": [
      "Int",
      "US"
    ],
    "duration": "11:26"
  },
  {
    "video_id": "Q62UwEPPnrg",
    "title": "Learn First Aid Vocabulary in English – It could save your life!",
    "video_tags": [
      "Int",
      "US"
    ],
    "duration": "12:18"
  },
  {
    "video_id": "0CmsVuvtqSM",
    "title": "[Eng Sub/HD 中文电影预告] 与神同行2 (Along With Gods 2)_角色版预告(Character Intro Video)_(신과 함께 - 인과 연) 캐릭터 예고편",
    "video_tags": [
      "Basic",
      "US"
    ],
    "duration": "02:34"
  },
  {
    "video_id": "7EgB__YratE",
    "title": "The Jesus And Mary Chain - Just Like Honey (Official Music Video)",
    "video_tags": [
      "Basic",
      "US"
    ],
    "duration": "03:03"
  },
  {
    "video_id": "8qGCleYV4cw",
    "title": "Getting Over It",
    "video_tags": [
      "Basic",
      "US"
    ],
    "duration": "07:03"
  },
  {
    "video_id": "f33opIjN_Ps",
    "title": "Jon Dorenbos on the Saints That Changed His Life",
    "video_tags": [
      "Basic",
      "UK"
    ],
    "duration": "06:19"
  },
  {
    "video_id": "ZHgVlRdO72U",
    "title": "CIVILIZATION VI - First Look: Japan",
    "video_tags": [
      "Int",
      "US"
    ],
    "duration": "01:55"
  },
  {
    "video_id": "gQOpmNuaPWQ",
    "title": "I Didn't Throw Up! | March Vlog",
    "video_tags": [
      "Int",
      "US"
    ],
    "duration": "15:30"
  },
  {
    "video_id": "9qyXocJvm6k",
    "title": "Anne Frank   The Life of a Young Girl",
    "video_tags": [
      "Advanced",
      "US"
    ],
    "duration": "45:08"
  },
  {
    "video_id": "t2mU6USTBRE",
    "title": "\"Weird Al\" Yankovic - Fat (Official Music Video)",
    "video_tags": [
      "Basic",
      "US"
    ],
    "duration": "04:56"
  }
]