[
  {
    "video_id": "zw9k19uZB5E",
    "title": "V-Ray for 3ds Max – Quick Tutorial: [GPU] High Resolution Rendering and Render Elements",
    "video_tags": [
      "Int",
      "US"
    ],
    "duration": "07:13"
  },
  {
    "video_id": "ax411Q_of0A",
    "title": "Reach More Viewers with Captions ft. Jessica Kellgren-Fozard",
    "video_tags": [
      "Int",
      "UK"
    ],
    "duration": "05:56"
  },
  {
    "video_id": "7kkRkhAXZGg",
    "title": "The data behind Hollywood's sexism | Stacy Smith",
    "video_tags": [
      "Int",
      "US"
    ],
    "duration": "15:45"
  },
  {
    "video_id": "f7DqQ5lOlaU",
    "title": "Tracy Morgan Was A \"Crack Dealer With A Heart Of Gold\"  - CONAN on TBS",
    "video_tags": [
      "Basic",
      "US"
    ],
    "duration": "07:08"
  },
  {
    "video_id": "mgsErxFEPSE",
    "title": "Why Comedy Matters",
    "video_tags": [
      "Int",
      "UK"
    ],
    "duration": "07:12"
  },
  {
    "video_id": "8mYxrdcKhFw",
    "title": "Breaking Thor with Chris Hemsworth",
    "video_tags": [
      "Basic",
      "US"
    ],
    "duration": "02:57"
  },
  {
    "video_id": "Z2_ssAGQmO4",
    "title": "How to Use and Counter Flying Machine | Clash Royale",
    "video_tags": [
      "Int",
      "US"
    ],
    "duration": "10:01"
  },
  {
    "video_id": "oV0zkMe1K8s",
    "title": "How Black Panther Should Have Ended - Animated Parody",
    "video_tags": [
      "Basic",
      "US"
    ],
    "duration": "04:22"
  },
  {
    "video_id": "VEe7NxB5Vo8",
    "title": "Why is the top flow faster over an Airfoil ?",
    "video_tags": [
      "Int",
      "US"
    ],
    "duration": "04:12"
  },
  {
    "video_id": "ssr8_yoU7qE",
    "title": "The 100TB Project",
    "video_tags": [
      "Int",
      "US"
    ],
    "duration": "05:54"
  },
  {
    "video_id": "xE7J0a47DCs",
    "title": "TWB S1R installation on Yamaha R1 2015",
    "video_tags": [
      "Int",
      "US"
    ],
    "duration": "06:31"
  },
  {
    "video_id": "CuXlBSuQbMo",
    "title": "Beto Announces 2020 Bid and Trump Attacks Him: A Closer Look",
    "video_tags": [
      "Int",
      "US"
    ],
    "duration": "11:48"
  },
  {
    "video_id": "DKPCBAlDw2A",
    "title": "The Chainsmokers - Everybody Hates Me (Official Video)",
    "video_tags": [
      "Basic",
      "US"
    ],
    "duration": "03:46"
  },
  {
    "video_id": "7eWGnJpf4Fk",
    "title": "Learn all about Windows Server 2019 Cluster Sets",
    "video_tags": [
      "Int",
      "US"
    ],
    "duration": "05:05"
  },
  {
    "video_id": "tohDycgc-H8",
    "title": "The Disappearance of Hatsune Miku ♡ English Cover【rachie】初音ミクの消失",
    "video_tags": [
      "Basic",
      "US"
    ],
    "duration": "05:11"
  },
  {
    "video_id": "H16B8UDdWzo",
    "title": "How to SPEAK ENGLISH like a NATIVE | Pronunciation and Fluency Lesson",
    "video_tags": [
      "Int",
      "UK"
    ],
    "duration": "14:43"
  }
]