[
  {
    "video_id": "t10q2I7RHWE",
    "title": "How to use 'yet' and 'not yet' - Learners' Questions",
    "video_tags": [
      "Basic",
      "UK"
    ],
    "duration": "03:05"
  },
  {
    "video_id": "W4yh5gNecwM",
    "title": "Candy Lovers Learn Disturbing Sugar Facts While Eating Candy",
    "video_tags": [
      "Int"
    ],
    "duration": "03:09"
  },
  {
    "video_id": "HNMQ_w7hXTA",
    "title": "The surprisingly charming science of your gut | Giulia Enders",
    "video_tags": [
      "Int",
      "US"
    ],
    "duration": "14:04"
  },
  {
    "video_id": "_ipyRaGAyyk",
    "title": "What Will The Earth Look Like In 100 Years?",
    "video_tags": [
      "Int",
      "US"
    ],
    "duration": "03:21"
  },
  {
    "video_id": "ym0XdHZrtHI",
    "title": "How Could You Walk Through Walls?",
    "video_tags": [
      "Int",
      "US"
    ],
    "duration": "04:15"
  },
  {
    "video_id": "uX-QIKhf5UU",
    "title": "Can You Have More Than One Personality?",
    "video_tags": [
      "Basic",
      "US"
    ],
    "duration": "03:44"
  },
  {
    "video_id": "lAmqsMQG3RM",
    "title": "Volcano | The Dr. Binocs Show | Learn Videos For Kids",
    "video_tags": [
      "Int",
      "US"
    ],
    "duration": "02:51"
  },
  {
    "video_id": "7fCRpR5f_f0",
    "title": "IELTS Speaking 3: Historic Place | Địa điểm lịch sử",
    "video_tags": [
      "Basic",
      "Other"
    ],
    "duration": "03:42"
  },
  {
    "video_id": "n9cKXZBYapQ",
    "title": "Brad Anderson, CEO of Best Buy at Zeitgeist '08",
    "video_tags": [
      "Basic",
      "US"
    ],
    "duration": "28:53"
  },
  {
    "video_id": "y7LXwGfvxwo",
    "title": "What if my neighbor's kid was genetically modified? | Paul Knoepfler | TEDxVienna",
    "video_tags": [
      "Int",
      "US"
    ],
    "duration": "18:10"
  },
  {
    "video_id": "dRX0wDNK6S4",
    "title": "Kane Brown - Heaven (Official Music Video)",
    "video_tags": [
      "Basic",
      "US"
    ],
    "duration": "02:56"
  },
  {
    "video_id": "RbNqU2K0qzo",
    "title": "The coolest animal you know nothing about ... and how we can save it | Patrícia Medici",
    "video_tags": [
      "Int",
      "US"
    ],
    "duration": "11:33"
  },
  {
    "video_id": "OKGX7gQnxpc",
    "title": "3-Minute Workout Before Sleep to Slim Down Your Legs",
    "video_tags": [
      "Int",
      "US"
    ],
    "duration": "10:01"
  },
  {
    "video_id": "6B8FySbsUsM",
    "title": "22. Kurosawa and Rashomon",
    "video_tags": [
      "Advanced",
      "US"
    ],
    "duration": "58:46"
  },
  {
    "video_id": "dXFyzPN3v3Q",
    "title": "Intel: One Company, One Voice",
    "video_tags": [
      "Basic",
      "US"
    ],
    "duration": "03:42"
  },
  {
    "video_id": "nxtIRArhVD4",
    "title": "Jennifer Lopez - Booty ft. Iggy Azalea (Official Video)",
    "video_tags": [
      "Basic",
      "US"
    ],
    "duration": "04:17"
  }
]