[
  {
    "video_id": "caZpJOtYz-o",
    "title": "Tiësto, Gucci Mane, Sevenn - BOOM (Official Video)",
    "video_tags": [
      "Basic",
      "US"
    ],
    "duration": "03:02"
  },
  {
    "video_id": "rdWjlA3XsV0",
    "title": "Study English - Series 1, Episode 9: ADHD",
    "video_tags": [
      "Int",
      "AU"
    ],
    "duration": "09:55"
  },
  {
    "video_id": "Ur-8ibFvAY4",
    "title": "Tokyo Ghoul IN 5 MINUTES",
    "video_tags": [
      "Int"
    ],
    "duration": "05:59"
  },
  {
    "video_id": "BYrcTd-u3N4",
    "title": "part 1of 6 -Revolution- Critical moment 4/6 Ancient Rome The Rise and Fall of an Empire",
    "video_tags": [
      "Advanced"
    ],
    "duration": "10:00"
  },
  {
    "video_id": "WpN9jOo-bvA",
    "title": "English Christian Video \"The Lord Is Knocking\" | Welcome the Return of the Lord (Skit)",
    "video_tags": [
      "Int",
      "US"
    ],
    "duration": "23:54"
  },
  {
    "video_id": "bPlvYNhlcVw",
    "title": "Shout it from the rooftops: The English We Speak",
    "video_tags": [
      "Basic",
      "UK"
    ],
    "duration": "02:13"
  },
  {
    "video_id": "HqZ4EoeJIlQ",
    "title": "伏地挺身正確的作法（怎麼練胸部）(subs)",
    "video_tags": [
      "Basic",
      "US"
    ],
    "duration": "04:54"
  },
  {
    "video_id": "UZ8I_dp4J_s",
    "title": "8 Great Things to do in London | Kaplan International English",
    "video_tags": [
      "Basic",
      "UK"
    ],
    "duration": "01:43"
  },
  {
    "video_id": "S89dobHBnkY",
    "title": "Peter's Odd Rehearsal Needs | Season 15 Ep. 4 | FAMILY GUY",
    "video_tags": [
      "Basic",
      "US"
    ],
    "duration": "01:07"
  },
  {
    "video_id": "dDIJhjRPg-A",
    "title": "we crashed a party and got (slightly) naked?!?!? STORYTIME!",
    "video_tags": [
      "Int",
      "US"
    ],
    "duration": "10:10"
  },
  {
    "video_id": "yzbBAkbgfW4",
    "title": "Make your PHOTOS & VIDEOS more PROFESSIONAL!",
    "video_tags": [
      "Int",
      "US"
    ],
    "duration": "11:51"
  },
  {
    "video_id": "6ixGvIOBPC4",
    "title": "China Bans Erotic Banana Eating",
    "video_tags": [
      "Int",
      "US"
    ],
    "duration": "05:31"
  },
  {
    "video_id": "H03o2WCBoDU",
    "title": "The real reason manufacturing jobs are disappearing | Augie Picado",
    "video_tags": [
      "Int",
      "US"
    ],
    "duration": "12:06"
  },
  {
    "video_id": "Qao76IPXW-E",
    "title": "To solve the world's biggest problems, invest in women and girls | Musimbi Kanyoro",
    "video_tags": [
      "Int",
      "US"
    ],
    "duration": "14:30"
  },
  {
    "video_id": "V3QaDTo2_7c",
    "title": "World of Tanks - Best Replays of the Week International #64",
    "video_tags": [
      "Int",
      "US"
    ],
    "duration": "10:46"
  },
  {
    "video_id": "0NGei3H8yRk",
    "title": "Why do we itch? - Emma Bryce",
    "video_tags": [
      "Int",
      "US"
    ],
    "duration": "04:44"
  }
]