[
  {
    "video_id": "iGbpvtmVxBw",
    "title": "Template Applications Using CMSIS and Middleware",
    "video_tags": [
      "Int"
    ],
    "duration": "03:32"
  },
  {
    "video_id": "LI1CusL7Ceo",
    "title": "Holden, JD, and the Red Cap - The Catcher in the Rye Part 2: Crash Course English Literature #7",
    "video_tags": [
      "Int"
    ],
    "duration": "08:21"
  },
  {
    "video_id": "R2zXxQHBpd8",
    "title": "joji - will he",
    "video_tags": [
      "Basic",
      "US"
    ],
    "duration": "03:23"
  },
  {
    "video_id": "OC2iwQcfZwA",
    "title": "Omega 3s, Prostate Cancer, and Atrial Fibrillation",
    "video_tags": [
      "Int",
      "US"
    ],
    "duration": "04:10"
  },
  {
    "video_id": "ytRH2sV5wv8",
    "title": "Hyperloop’s first full-scale passenger capsule | CNBC Reports",
    "video_tags": [
      "Int",
      "US"
    ],
    "duration": "02:49"
  },
  {
    "video_id": "k4vRFodAqWo",
    "title": "Billie Eilish Gets Candid About Tourette Syndrome",
    "video_tags": [
      "Basic",
      "US"
    ],
    "duration": "03:52"
  },
  {
    "video_id": "HmRoek-Q-Lo",
    "title": "Here's Why Costco Really Checks Your Receipt Before You Leave",
    "video_tags": [
      "Int",
      "US"
    ],
    "duration": "03:30"
  },
  {
    "video_id": "Qv_eZHByTJw",
    "title": "Taiwan Night Market - Eating Taiwanese Street Food in Taipei along Raohe Street (饒河夜市)",
    "video_tags": [
      "Int"
    ],
    "duration": "14:01"
  },
  {
    "video_id": "uWfLwKH_Eko",
    "title": "Ethan Nadelmann: Why we need to end the War on Drugs",
    "video_tags": [
      "Advanced",
      "US"
    ],
    "duration": "17:31"
  },
  {
    "video_id": "Hg5dOEvjEYU",
    "title": "PARENTS REACT TO XXXTENTACION",
    "video_tags": [
      "Int",
      "US"
    ],
    "duration": "10:39"
  },
  {
    "video_id": "PkjLMWS3U4Q",
    "title": "Jimmy Kimmel’s Tribute to Matt Damon at the Oscars",
    "video_tags": [
      "Basic",
      "US"
    ],
    "duration": "02:51"
  },
  {
    "video_id": "hcwSQNfwDaQ",
    "title": "Who Will Lead The Western World In 2017?",
    "video_tags": [
      "Int",
      "US"
    ],
    "duration": "03:58"
  },
  {
    "video_id": "r0c1XilUIM4",
    "title": "Is Religion Banned in China?",
    "video_tags": [
      "Int"
    ],
    "duration": "10:12"
  },
  {
    "video_id": "F1i2bjq9vUI",
    "title": "Build Twice the Muscle with 1/2 the Weight!",
    "video_tags": [
      "Int",
      "US"
    ],
    "duration": "04:58"
  },
  {
    "video_id": "Orumw-PyNjw",
    "title": "The Integumentary System, Part 1 - Skin Deep: Crash Course A&P #6",
    "video_tags": [
      "Advanced"
    ],
    "duration": "09:40"
  },
  {
    "video_id": "Drp3E6ea7VE",
    "title": "English Vocabulary Essentials with Perfect Pronunciation | Learn English with Rachel's English 7/11",
    "video_tags": [
      "Int",
      "US"
    ],
    "duration": "19:25"
  }
]