[
  {
    "video_id": "Zi_XLOBDo_Y",
    "title": "Michael Jackson - Billie Jean (Official Video)",
    "video_tags": [
      "Basic",
      "US"
    ],
    "duration": "04:56"
  },
  {
    "video_id": "Z0vLiQLpsc8",
    "title": "Jimmy Kimmel on School Shooting in Parkland, Florida",
    "video_tags": [
      "Int",
      "US"
    ],
    "duration": "04:50"
  },
  {
    "video_id": "v7aib21s2N8",
    "title": "Harvard Scientists REVERSE Aging In Mice. People Next...",
    "video_tags": [
      "Int",
      "US"
    ],
    "duration": "09:22"
  },
  {
    "video_id": "0DSsPAUhRsA",
    "title": "【ENG SUB FULL】Keep Running EP.1 20170414 [ ZhejiangTV HD1080P ]",
    "video_tags": [
      "Advanced",
      "US"
    ],
    "duration": "01:48:43"
  },
  {
    "video_id": "oCV2DBhNKf8",
    "title": "WHAT IS GROWTH HACKING? - Entrepreneurship 101",
    "video_tags": [
      "Int",
      "US"
    ],
    "duration": "04:38"
  },
  {
    "video_id": "L90R6PtxFKE",
    "title": "Are Rich People Worse Humans?",
    "video_tags": [
      "Int",
      "US"
    ],
    "duration": "04:22"
  },
  {
    "video_id": "feyHxRFOv_E",
    "title": "ENTEI RAID GUIDE! HOW TO COUNTER AND CATCH ENTEI IN POKÉMON GO!",
    "video_tags": [
      "Int",
      "US"
    ],
    "duration": "16:02"
  },
  {
    "video_id": "h9deGh8_tEc",
    "title": "The boost students need to overcome obstacles | Anindya Kundu",
    "video_tags": [
      "Int",
      "US"
    ],
    "duration": "07:06"
  },
  {
    "video_id": "9nJaDK7jKro",
    "title": "MIT Quest for Intelligence Launch: Featured Innovator",
    "video_tags": [
      "Int",
      "US"
    ],
    "duration": "20:15"
  },
  {
    "video_id": "SFW0TEFKCxk",
    "title": "Angela Belcher: Using nature to grow batteries",
    "video_tags": [
      "Int",
      "US"
    ],
    "duration": "10:26"
  },
  {
    "video_id": "TNtIA2fgHfg",
    "title": "Peking Duk ft. Nicole Millar - \"High\" (Official Video)",
    "video_tags": [
      "Basic",
      "US"
    ],
    "duration": "04:00"
  },
  {
    "video_id": "kWh0t1fX_EY",
    "title": "Motorcycle Lane Filtering in New South Wales",
    "video_tags": [
      "Basic",
      "AU"
    ],
    "duration": "02:37"
  },
  {
    "video_id": "GDgaiS4jYsQ",
    "title": "Bad Boy (\"Bad Boy\" Short Film #1)",
    "video_tags": [
      "Basic",
      "US"
    ],
    "duration": "04:57"
  },
  {
    "video_id": "TTfe2Manwmo",
    "title": "OCEAN'S 8 Official Trailer (2018) Rihanna, Anne Hathaway Action Movie HD",
    "video_tags": [
      "Basic",
      "US"
    ],
    "duration": "02:36"
  },
  {
    "video_id": "3sK3wJAxGfs",
    "title": "If You Want to Change the World, Start Off by Making Your Bed - William McRaven, US Navy Admiral",
    "video_tags": [
      "Int",
      "US"
    ],
    "duration": "06:01"
  },
  {
    "video_id": "e3h6es6zh1c",
    "title": "Key & Peele - Office Homophobe",
    "video_tags": [
      "Int",
      "US"
    ],
    "duration": "03:43"
  }
]